stubgenlib/__init__.py
stubgenlib/build.py
stubgenlib/cpptypeconvert.py
stubgenlib/moduleinspect.py
stubgenlib/notifier.py
stubgenlib/py.typed
stubgenlib/test_helpers.py
stubgenlib/utils.py
stubgenlib/siggen/__init__.py
stubgenlib/siggen/advanced.py
stubgenlib/siggen/boost.py
stubgenlib/siggen/default.py
stubgenlib/siggen/docstring.py
stubgenlib/siggen/sigfixer.py
stubgenlib/stubgen/__init__.py
stubgenlib/stubgen/delegate.py
stubgenlib-0.3.0.dist-info/METADATA
stubgenlib-0.3.0.dist-info/WHEEL
stubgenlib-0.3.0.dist-info/RECORD
